kodi_addon_checker/__init__.py
kodi_addon_checker/__main__.py
kodi_addon_checker/check_addon.py
kodi_addon_checker/check_addon_branches.py
kodi_addon_checker/check_allowed_versions.py
kodi_addon_checker/check_artwork.py
kodi_addon_checker/check_dependencies.py
kodi_addon_checker/check_entrypoint.py
kodi_addon_checker/check_files.py
kodi_addon_checker/check_py3_compatibility.py
kodi_addon_checker/check_repo.py
kodi_addon_checker/check_string.py
kodi_addon_checker/check_url.py
kodi_addon_checker/config.py
kodi_addon_checker/handle_files.py
kodi_addon_checker/logger.py
kodi_addon_checker/record.py
kodi_addon_checker/report.py
kodi_addon_checker/reporter.py
kodi_addon_checker/schema_validation.py
kodi_addon_checker/versions.py
kodi_addon_checker/addons/Addon.py
kodi_addon_checker/addons/AddonDependency.py
kodi_addon_checker/addons/Repository.py
kodi_addon_checker/addons/__init__.py
kodi_addon_checker/common/__init__.py
kodi_addon_checker/common/decorators.py
kodi_addon_checker/plugins/__init__.py
kodi_addon_checker/plugins/array_reporter.py
kodi_addon_checker/plugins/console_reporter.py
kodi_addon_checker/plugins/log_reporter.py
kodi_addon_checker/xml_schema/addon.xsd
kodi_addon_checker/xml_schema/gotham_images.xsd
kodi_addon_checker/xml_schema/gotham_metadata.xsd
kodi_addon_checker/xml_schema/gotham_pluginsource.xsd
kodi_addon_checker/xml_schema/gotham_pythonscript.xsd
kodi_addon_checker/xml_schema/gotham_repository.xsd
kodi_addon_checker/xml_schema/gotham_scraper.xsd
kodi_addon_checker/xml_schema/gotham_script.xsd
kodi_addon_checker/xml_schema/gotham_service.xsd
kodi_addon_checker/xml_schema/gotham_skin.xsd
kodi_addon_checker/xml_schema/gotham_uisounds.xsd
kodi_addon_checker/xml_schema/gotham_webinterface.xsd
kodi_addon_checker/xml_schema/isengard_contextitem.xsd
kodi_addon_checker/xml_schema/isengard_language.xsd
kodi_addon_checker/xml_schema/jarvis_contextitem.xsd
kodi_addon_checker/xml_schema/krypton_controller.xsd
kodi_addon_checker/xml_schema/leia_font.xsd
kodi_addon_checker-0.0.36.dist-info/LICENSE
kodi_addon_checker-0.0.36.dist-info/METADATA
kodi_addon_checker-0.0.36.dist-info/WHEEL
kodi_addon_checker-0.0.36.dist-info/entry_points.txt
kodi_addon_checker-0.0.36.dist-info/top_level.txt
kodi_addon_checker-0.0.36.dist-info/RECORD
