Metadata-Version: 2.1
Name: kodi-addon-checker
Version: 0.0.36
Summary: Check kodi addons or whole kodi repositories for errors and best practices.
Home-page: https://github.com/xbmc/addon-check
Download-URL: https://github.com/xbmc/addon-check/archive/master.zip
Author: Team Kodi
Keywords: kodi add-on add-on_checker
Classifier: Operating System :: POSIX :: Linux
Classifier: License :: OSI Approved :: GNU General Public License v3 (GPLv3)
Classifier: Operating System :: Microsoft :: Windows
Classifier: Operating System :: MacOS
Classifier: Development Status :: 5 - Production/Stable
Classifier: Environment :: Console
Classifier: Intended Audience :: Developers
Classifier: Topic :: Utilities
Classifier: Programming Language :: Python :: 3.8
Classifier: Programming Language :: Python :: 3.9
Classifier: Programming Language :: Python :: 3.10
Classifier: Programming Language :: Python :: 3.11
Classifier: Programming Language :: Python :: 3.12
Classifier: Programming Language :: Python :: 3.13
Requires-Python: >=3.5
License-File: LICENSE
Requires-Dist: packaging
Requires-Dist: pillow
Requires-Dist: polib
Requires-Dist: requests >=2.25.0
Requires-Dist: radon
Requires-Dist: urllib3 >=1.26.0
Requires-Dist: xmlschema
